ml_confs/__init__.py
ml_confs/lib.py
ml_confs-0.0.4.dist-info/METADATA
ml_confs-0.0.4.dist-info/WHEEL
ml_confs-0.0.4.dist-info/licenses/LICENSE
ml_confs-0.0.4.dist-info/RECORD
