Metadata-Version: 2.1
Name: ml_confs
Version: 0.0.4
Summary: A utility to handle configurations for machine learning pipelines
Project-URL: Homepage, https://github.com/Pietronvll/ml_confs
Author-email: Pietro Novelli <pietronvll@gmail.com>
License-File: LICENSE
Classifier: Operating System :: OS Independent
Classifier: Programming Language :: Python :: 3
Requires-Python: >=3.9
Requires-Dist: pyyaml>=6.0
Requires-Dist: rich>=13.0
Provides-Extra: dev
Requires-Dist: jax; extra == 'dev'
Requires-Dist: jaxlib; extra == 'dev'
Requires-Dist: lazydocs; extra == 'dev'
Requires-Dist: pytest; extra == 'dev'
Provides-Extra: jax
Requires-Dist: jax; extra == 'jax'
Requires-Dist: jaxlib; extra == 'jax'
